dekvenv-0.1.50.dist-info/METADATA
dekvenv-0.1.50.dist-info/WHEEL
dekvenv-0.1.50.dist-info/entry_points.txt
dekvenv-0.1.50.dist-info/licenses/LICENSE
dekvenv/__entry__.py
dekvenv/__init__.py
dekvenv/command.py
dekvenv/fix/__init__.py
dekvenv/fix/command.py
dekvenv/main/__init__.py
dekvenv/main/command.py
dekvenv/main/core.py
dekvenv/pdm/__init__.py
dekvenv/pdm/command.py
dekvenv/pdm/core.py
dekvenv/pipconf/__init__.py
dekvenv/pipconf/command.py
dekvenv/pipconf/core.py
dekvenv/pypirc/__init__.py
dekvenv/pypirc/command.py
dekvenv/pypirc/core.py
dekvenv/script/__init__.py
dekvenv/script/command.py
dekvenv/script/core.py
dekvenv/script/res/pyproject.toml-tpl
dekvenv/utils/__init__.py
dekvenv/utils/common.py
dekvenv-0.1.50.dist-info/RECORD
