Metadata-Version: 2.1
Name: dekvenv
Version: 0.1.50
Author-Email: sanzenwin <sanzenwin@gmail.com>
License: MIT
Requires-Python: >=3.7
Requires-Dist: virtualenv<21.0.0
Requires-Dist: dektools[jsonpath]<1.0.0
Provides-Extra: core
Requires-Dist: build<=0.10.0; extra == "core"
Requires-Dist: toml<=0.10.2; extra == "core"
Requires-Dist: packaging<24.0; extra == "core"
Provides-Extra: pdm
Requires-Dist: pdm; extra == "pdm"
Provides-Extra: all
Requires-Dist: dekvenv[core,pdm]; extra == "all"
